README.md
aio_typesense/__init__.py
aio_typesense/api_call.py
aio_typesense/client.py
aio_typesense/collections.py
aio_typesense/documents.py
aio_typesense/types.py
aio_typesense-0.1.0.dist-info/WHEEL
aio_typesense-0.1.0.dist-info/METADATA
aio_typesense-0.1.0.dist-info/RECORD
