Metadata-Version: 2.1
Name: aio-typesense
Version: 0.1.0
Summary: Async library for Typesense
Home-page: https://github.com/devtud/aio_typesense
License: MIT
Keywords: asyncio,typesense
Author: devtud
Author-email: devtud@gmail.com
Requires-Python: >=3.6,<4.0
Classifier: Development Status :: 3 - Alpha
Classifier: Framework :: AsyncIO
Classifier: Intended Audience :: Developers
Classifier: License :: OSI Approved :: MIT License
Classifier: Programming Language :: Python :: 3
Classifier: Programming Language :: Python :: 3 :: Only
Classifier: Programming Language :: Python :: 3.6
Classifier: Programming Language :: Python :: 3.7
Classifier: Programming Language :: Python :: 3.8
Classifier: Programming Language :: Python :: 3.9
Classifier: Topic :: Software Development :: Libraries :: Application Frameworks
Requires-Dist: httpx
Requires-Dist: typing-extensions (>=3.7.4,<4.0.0); python_version >= "3.6" and python_version < "3.8"
Project-URL: Repository, https://github.com/devtud/aio_typesense
